AIRi
MANIFEST.in
README
setup.py
airi/__init__.py
airi/api.py
airi/jinja.py
airi/pair.py
airi/server.py
airi/settings.py
airi/stream.py
airi/webcam.py
airi.egg-info/PKG-INFO
airi.egg-info/SOURCES.txt
airi.egg-info/dependency_links.txt
airi.egg-info/not-zip-safe
airi.egg-info/top_level.txt
airi/camera/__init__.py
airi/camera/airicamera.py
airi/camera/optieyes.py
airi/camera/protocol.py
airi/media/airi.swf
airi/media/configure.html
airi/media/devices.html
airi/media/index.html
airi/media/scan.html
airi/media/video.html
airi/media/css/airi-jquery.mobile.css
airi/media/css/airi.css
airi/media/css/jquery.mobile-1.0a4.css
airi/media/css/cupertino/jquery-ui-1.8.10.custom.css
airi/media/css/cupertino/images/ui-bg_diagonals-thick_90_eeeeee_40x40.png
airi/media/css/cupertino/images/ui-bg_flat_15_cd0a0a_40x100.png
airi/media/css/cupertino/images/ui-bg_glass_100_e4f1fb_1x400.png
airi/media/css/cupertino/images/ui-bg_glass_50_3baae3_1x400.png
airi/media/css/cupertino/images/ui-bg_glass_80_d7ebf9_1x400.png
airi/media/css/cupertino/images/ui-bg_highlight-hard_100_f2f5f7_1x100.png
airi/media/css/cupertino/images/ui-bg_highlight-hard_70_000000_1x100.png
airi/media/css/cupertino/images/ui-bg_highlight-soft_100_deedf7_1x100.png
airi/media/css/cupertino/images/ui-bg_highlight-soft_25_ffef8f_1x100.png
airi/media/css/cupertino/images/ui-icons_2694e8_256x240.png
airi/media/css/cupertino/images/ui-icons_2e83ff_256x240.png
airi/media/css/cupertino/images/ui-icons_3d80b3_256x240.png
airi/media/css/cupertino/images/ui-icons_72a7cf_256x240.png
airi/media/css/cupertino/images/ui-icons_ffffff_256x240.png
airi/media/css/images/ajax-loader.png
airi/media/css/images/icon-search-black.png
airi/media/css/images/icons-18-black.png
airi/media/css/images/icons-18-white.png
airi/media/css/images/icons-36-black.png
airi/media/css/images/icons-36-white.png
airi/media/images/aircable-logo.png
airi/media/images/airi-icons.png
airi/media/images/loading.gif
airi/media/images/wide-header-bg.png
airi/media/js/Stream.js
airi/media/js/base64.js
airi/media/js/browser_faster.js
airi/media/js/custom.js
airi/media/js/jquery-1.4.4.min.js
