Metadata-Version: 1.0
Name: airi
Version: 0.1.0
Summary: AIRi software package
Home-page: https://github.com/manuelnaranjo/AIRi
Author: Naranjo Manuel Francisco
Author-email: manuel@aircable.net
License: Apache V2
Keywords: airi bluetooth twisted
Platform: UNKNOWN
Classifier: Development Status :: 3 - Alpha
Classifier: Environment :: Console
Classifier: Environment :: Web Environment
Classifier: Framework :: Twisted
Classifier: Topic :: Communications
Classifier: Topic :: Multimedia :: Video :: Capture
Classifier: License :: OSI Approved :: Apache Software License
Classifier: Natural Language :: English
